simp_sexp.py
simp_sexp-0.3.0.dist-info/licenses/LICENSE
simp_sexp-0.3.0.dist-info/METADATA
simp_sexp-0.3.0.dist-info/WHEEL
simp_sexp-0.3.0.dist-info/top_level.txt
simp_sexp-0.3.0.dist-info/RECORD
