Metadata-Version: 2.4
Name: simp_sexp
Version: 0.3.0
Summary: A simple S-expression parser
Author-email: Dave Vandenbout <dave@vdb.name>
License: MIT
Project-URL: Homepage, https://github.com/devbisme/simp_sexp
Project-URL: Documentation, https://github.com/devbisme/simp_sexp#readme
Project-URL: Bug Tracker, https://github.com/devbisme/simp_sexp/issues
Project-URL: Source Code, https://github.com/devbisme/simp_sexp
Keywords: s-expression,sexp,lisp,KiCad,serialization
Classifier: Development Status :: 3 - Alpha
Classifier: Intended Audience :: Developers
Classifier: Intended Audience :: Science/Research
Classifier: License :: OSI Approved :: MIT License
Classifier: Operating System :: OS Independent
Classifier: Programming Language :: Python
Classifier: Programming Language :: Python :: 3
Classifier: Programming Language :: Python :: 3.6
Classifier: Programming Language :: Python :: 3.7
Classifier: Programming Language :: Python :: 3.8
Classifier: Programming Language :: Python :: 3.9
Classifier: Programming Language :: Python :: 3.10
Classifier: Programming Language :: Python :: 3.11
Classifier: Programming Language :: Python :: 3.12
Classifier: Programming Language :: Python :: 3.13
Classifier: Programming Language :: Python :: Implementation :: CPython
Classifier: Topic :: Software Development :: Libraries
Classifier: Topic :: Software Development :: Libraries :: Python Modules
Classifier: Topic :: Text Processing
Classifier: Topic :: Text Processing :: Markup
Classifier: Typing :: Typed
Requires-Python: >=3.6
License-File: LICENSE
Provides-Extra: dev
Requires-Dist: pytest; extra == "dev"
Requires-Dist: tox>=4.0.0; extra == "dev"
Dynamic: license-file
